vim_client/__init__.py
vim_client/cli.py
vim_client-1.0.5.dist-info/LICENSE
vim_client-1.0.5.dist-info/METADATA
vim_client-1.0.5.dist-info/WHEEL
vim_client-1.0.5.dist-info/entry_points.txt
vim_client-1.0.5.dist-info/top_level.txt
vim_client-1.0.5.dist-info/RECORD
