Metadata-Version: 2.1
Name: vim-client
Version: 1.0.5
Summary: Connect to Vim server, edit files, evaluate Vim expressions, and send commands to Vim.
Home-page: https://github.com/jamescherti/vim-client
Author: James Cherti
License: UNKNOWN
Project-URL: Bug Reports, https://github.com/jamescherti/vim-client/issues
Project-URL: Source, https://github.com/jamescherti/vim-client
Keywords: vim,server,remote,edit,client,clientserver
Platform: UNKNOWN
Classifier: Development Status :: 5 - Production/Stable
Classifier: Intended Audience :: Developers
Classifier: License :: OSI Approved :: MIT License
Classifier: Topic :: Software Development :: Libraries :: Python Modules
Classifier: Topic :: Text Editors
Classifier: Operating System :: Unix
Classifier: Operating System :: POSIX :: Linux
Classifier: Operating System :: POSIX :: BSD
Classifier: Programming Language :: Python :: 3
Classifier: Programming Language :: Python :: 3.6
Classifier: Programming Language :: Python :: 3.7
Classifier: Programming Language :: Python :: 3.8
Classifier: Programming Language :: Python :: 3.9
Classifier: Programming Language :: Python :: 3 :: Only
Requires-Python: >=3.6, <4
